applyx/__init__.py
applyx/_version.py
applyx/exception.py
applyx/filesystem.py
applyx/image.py
applyx/jinja2.py
applyx/log.py
applyx/mongo.py
applyx/mysql.py
applyx/redis.py
applyx/service.py
applyx/storage.py
applyx/utils.py
applyx/aio/__init__.py
applyx/aio/filesystem.py
applyx/aio/redis.py
applyx/aio/utils.py
applyx/celery/__init__.py
applyx/celery/base.py
applyx/celery/celeryconfig_sample.py
applyx/command/__init__.py
applyx/command/base.py
applyx/command/clean.py
applyx/command/gunicorn.py
applyx/command/mcp.py
applyx/command/script.py
applyx/command/shell.py
applyx/command/web.py
applyx/conf/__init__.py
applyx/conf/config.py
applyx/conf/default.yaml
applyx/entrypoint/__init__.py
applyx/entrypoint/console.py
applyx/entrypoint/workspace/README.md
applyx/entrypoint/workspace/project/__init__.py
applyx/entrypoint/workspace/project/__main__.py
applyx/entrypoint/workspace/project/account/__init__.py
applyx/entrypoint/workspace/project/account/models.py
applyx/entrypoint/workspace/project/account/services.py
applyx/entrypoint/workspace/project/celery/__init__.py
applyx/entrypoint/workspace/project/celery/beat.py
applyx/entrypoint/workspace/project/celery/config.py
applyx/entrypoint/workspace/project/celery/worker.py
applyx/entrypoint/workspace/project/celery/tasks/__init__.py
applyx/entrypoint/workspace/project/celery/tasks/demo.py
applyx/entrypoint/workspace/project/conf/settings.yaml
applyx/entrypoint/workspace/project/scripts/demo.py
applyx/entrypoint/workspace/project/web/builder.py
applyx/entrypoint/workspace/project/web/routes/api.py
applyx/entrypoint/workspace/project/web/routes/page.py
applyx/entrypoint/workspace/project/web/routes/webhook.py
applyx/gunicorn/__init__.py
applyx/gunicorn/app.py
applyx/gunicorn/default.yaml
applyx/mcp/builder.py
applyx/web/__init__.py
applyx/web/builder.py
applyx/web/default.yaml
applyx/web/middlewares.py
applyx-0.4.10.dist-info/licenses/LICENSE
applyx-0.4.10.dist-info/METADATA
applyx-0.4.10.dist-info/WHEEL
applyx-0.4.10.dist-info/entry_points.txt
applyx-0.4.10.dist-info/top_level.txt
applyx-0.4.10.dist-info/RECORD
